{
	"backtrace" : 0,
	"backtraceGraph" : 
	{
		"commands" : [],
		"files" : 
		[
			"build_exercises/practice/isogram/CMakeLists.txt"
		],
		"nodes" : 
		[
			{
				"file" : 0
			}
		]
	},
	"dependencies" : 
	[
		{
			"id" : "isogram::@953c035009ff4b49c981"
		},
		{
			"id" : "test_isogram::@953c035009ff4b49c981"
		},
		{
			"id" : "ZERO_CHECK::@6890427a1f51a3e7e1df"
		}
	],
	"id" : "ALL_BUILD::@953c035009ff4b49c981",
	"isGeneratorProvided" : true,
	"name" : "ALL_BUILD",
	"paths" : 
	{
		"build" : "build_exercises/practice/isogram",
		"source" : "build_exercises/practice/isogram"
	},
	"sources" : [],
	"type" : "UTILITY"
}
