{
	"backtrace" : 0,
	"backtraceGraph" : 
	{
		"commands" : [],
		"files" : 
		[
			"build_exercises/practice/pop-count/CMakeLists.txt"
		],
		"nodes" : 
		[
			{
				"file" : 0
			}
		]
	},
	"dependencies" : 
	[
		{
			"id" : "pop-count::@cf90ba49888b5b253e6d"
		},
		{
			"id" : "test_pop-count::@cf90ba49888b5b253e6d"
		},
		{
			"id" : "ZERO_CHECK::@6890427a1f51a3e7e1df"
		}
	],
	"id" : "ALL_BUILD::@cf90ba49888b5b253e6d",
	"isGeneratorProvided" : true,
	"name" : "ALL_BUILD",
	"paths" : 
	{
		"build" : "build_exercises/practice/pop-count",
		"source" : "build_exercises/practice/pop-count"
	},
	"sources" : [],
	"type" : "UTILITY"
}
